octopus_common/__init__.py
octopus_common/constant/Constants.py
octopus_common/constant/__init__.py
octopus_common/enums/ErrorCode.py
octopus_common/enums/__init__.py
octopus_common/model/BaseResponse.py
octopus_common/model/BizException.py
octopus_common/model/Crawler.py
octopus_common/model/Result.py
octopus_common/model/ResultDetail.py
octopus_common/model/__init__.py
octopus_common/util/__init__.py
octopus_common/util/scan_spiders.py
octopus_common_common_python-1.0.4.dist-info/METADATA
octopus_common_common_python-1.0.4.dist-info/WHEEL
octopus_common_common_python-1.0.4.dist-info/top_level.txt
octopus_common_common_python-1.0.4.dist-info/RECORD
