Metadata-Version: 2.1
Name: octopus-common-common-python
Version: 1.0.4
Summary: UNKNOWN
Home-page: UNKNOWN
Author: xzhao32
Author-email: xzhao32@trip.com
License: UNKNOWN
Platform: UNKNOWN
Classifier: Programming Language :: Python :: 3
Classifier: License :: OSI Approved :: MIT License
Classifier: Operating System :: OS Independent
Requires-Python: >=3.6
Requires-Dist: Flask==3.0.3
Requires-Dist: requests==2.32.3
